grizzlaxy/__init__.py
grizzlaxy/auth.py
grizzlaxy/cli.py
grizzlaxy/components/__init__.py
grizzlaxy/components/editor.js
grizzlaxy/components/editor.py
grizzlaxy/config.py
grizzlaxy/core.py
grizzlaxy/find.py
grizzlaxy/index-style.css
grizzlaxy/index-template.html
grizzlaxy/index.py
grizzlaxy/reload.py
grizzlaxy/utils.py
grizzlaxy/version.py
grizzlaxy-0.4.0.dist-info/LICENSE
grizzlaxy-0.4.0.dist-info/METADATA
grizzlaxy-0.4.0.dist-info/WHEEL
grizzlaxy-0.4.0.dist-info/entry_points.txt
grizzlaxy-0.4.0.dist-info/RECORD
