Metadata-Version: 2.1
Name: grizzlaxy
Version: 0.4.0
Summary: Create an app from a galaxy of starbears
License: MIT
Author: Olivier Breuleux
Author-email: breuleux@gmail.com
Requires-Python: >=3.9,<4.0
Classifier: License :: OSI Approved :: MIT License
Classifier: Programming Language :: Python :: 3
Classifier: Programming Language :: Python :: 3.9
Classifier: Programming Language :: Python :: 3.10
Classifier: Programming Language :: Python :: 3.11
Classifier: Programming Language :: Python :: 3.12
Provides-Extra: sentry
Provides-Extra: yaml
Requires-Dist: authlib (>=1.2.0,<2.0.0)
Requires-Dist: gifnoc (>=0.3.0,<0.4.0)
Requires-Dist: httpx (>=0.24.1,<0.25.0)
Requires-Dist: itsdangerous (>=2.1.2,<3.0.0)
Requires-Dist: jurigged (>=0.5.5,<0.6.0)
Requires-Dist: ovld (>=0.3.2,<0.4.0)
Requires-Dist: pyyaml (>=6.0.1,<7.0.0) ; extra == "yaml"
Requires-Dist: sentry-sdk[starlette] (>=1.35.0,<2.0.0) ; extra == "sentry"
Requires-Dist: sse-starlette (>=1.8.2,<2.0.0)
Requires-Dist: starbear (>=0.1.7,<0.2.0)
